demogpt/__init__.py
demogpt/app.py
demogpt/chains/__init__.py
demogpt/chains/chains.py
demogpt/chains/prompts/__init__.py
demogpt/chains/prompts/about.py
demogpt/chains/prompts/app_type.py
demogpt/chains/prompts/combine.py
demogpt/chains/prompts/combine_v2.py
demogpt/chains/prompts/draft.py
demogpt/chains/prompts/feedback.py
demogpt/chains/prompts/final.py
demogpt/chains/prompts/how_to_use.py
demogpt/chains/prompts/imports.py
demogpt/chains/prompts/old_tasks.py
demogpt/chains/prompts/plan.py
demogpt/chains/prompts/plan1.py
demogpt/chains/prompts/plan_feedback.py
demogpt/chains/prompts/plan_refiner.py
demogpt/chains/prompts/plan_with_inputs.py
demogpt/chains/prompts/prompt_chat_refiner.py
demogpt/chains/prompts/refine.py
demogpt/chains/prompts/self_refinement/__init__.py
demogpt/chains/prompts/self_refinement/final_refiner.py
demogpt/chains/prompts/system_inputs.py
demogpt/chains/prompts/task_controller.py
demogpt/chains/prompts/task_list/__init__.py
demogpt/chains/prompts/task_list/chat.py
demogpt/chains/prompts/task_list/detailed_description.py
demogpt/chains/prompts/task_list/doc_load.py
demogpt/chains/prompts/task_list/doc_to_string.py
demogpt/chains/prompts/task_list/hub_bash.py
demogpt/chains/prompts/task_list/hub_llm_math.py
demogpt/chains/prompts/task_list/hub_meteo.py
demogpt/chains/prompts/task_list/hub_question_answering.py
demogpt/chains/prompts/task_list/pal_chain.py
demogpt/chains/prompts/task_list/path_to_file.py
demogpt/chains/prompts/task_list/prompt_list_parser.py
demogpt/chains/prompts/task_list/prompt_template.py
demogpt/chains/prompts/task_list/python_coder.py
demogpt/chains/prompts/task_list/react.py
demogpt/chains/prompts/task_list/router.py
demogpt/chains/prompts/task_list/search.py
demogpt/chains/prompts/task_list/search_chat.py
demogpt/chains/prompts/task_list/string_to_doc.py
demogpt/chains/prompts/task_list/summarize.py
demogpt/chains/prompts/task_list/ui_input_chat.py
demogpt/chains/prompts/task_list/ui_input_file.py
demogpt-1.2.7.dist-info/LICENSE
demogpt-1.2.7.dist-info/METADATA
demogpt-1.2.7.dist-info/WHEEL
demogpt-1.2.7.dist-info/entry_points.txt
demogpt-1.2.7.dist-info/RECORD
