Metadata-Version: 2.3
Name: demogpt
Version: 1.2.7
Summary: Autonomous AI Agent for Gen-AI App Generation 
License: MIT
Author: Melih Unsal
Author-email: melihunsal.ai@gmail.com
Requires-Python: >=3.8.1,<4.0.0
Classifier: License :: OSI Approved :: MIT License
Classifier: Programming Language :: Python :: 3
Classifier: Programming Language :: Python :: 3.9
Classifier: Programming Language :: Python :: 3.10
Classifier: Programming Language :: Python :: 3.11
Classifier: Programming Language :: Python :: 3.12
Classifier: Programming Language :: Python :: 3.13
Requires-Dist: altair (<5)
Requires-Dist: autopep8
Requires-Dist: duckduckgo-search (==6.3.2)
Requires-Dist: flake8
Requires-Dist: langchain
Requires-Dist: langchain_experimental
Requires-Dist: langchain_openai
Requires-Dist: numexpr
Requires-Dist: openai
Requires-Dist: pdf2image
Requires-Dist: pdfminer-six
Requires-Dist: pydantic (<2.0.0)
Requires-Dist: pyowm (==3.3.0)
Requires-Dist: python-dotenv
Requires-Dist: streamlit
Requires-Dist: tiktoken
Requires-Dist: unstructured
Requires-Dist: wikipedia (==1.4.0)
Project-URL: Homepage, https://github.com/melih-unsal/DemoGPT
